<?xml version="1.0" encoding="UTF-8"?>
<objects serializationModel="Studio.02.01.00">
	<object class="AudioFile" id="{f036e333-8979-493d-8b38-97d8698c3a69}">
		<property name="assetPath">
			<value>Boss Battle - Intro 1.wav</value>
		</property>
		<property name="frequencyInKHz">
			<value>44.0999985</value>
		</property>
		<property name="channelCount">
			<value>2</value>
		</property>
		<property name="length">
			<value>1.7142857142857142</value>
		</property>
		<relationship name="masterAssetFolder">
			<destination>{b227804b-e996-4e51-84b8-eca950151dce}</destination>
		</relationship>
	</object>
</objects>
